xagent/__init__.py
xagent/agent.py
xagent/x.py
x_web_crawler-0.1.6.dist-info/LICENSE
x_web_crawler-0.1.6.dist-info/METADATA
x_web_crawler-0.1.6.dist-info/WHEEL
x_web_crawler-0.1.6.dist-info/entry_points.txt
x_web_crawler-0.1.6.dist-info/top_level.txt
x_web_crawler-0.1.6.dist-info/RECORD
