Metadata-Version: 2.1
Name: x-web-crawler
Version: 0.1.6
Summary: A web crawler for x.com
Home-page: https://github.com/jacobsomer/autofollow
Author: Jacob Somer
Author-email: somerjacob@gmail.com
Classifier: Programming Language :: Python :: 3
Classifier: License :: OSI Approved :: MIT License
Classifier: Operating System :: OS Independent
Requires-Python: >=3.6
License-File: LICENSE
Requires-Dist: selenium
